tests/__init__.py
tests/test_tw5_server.py
tw5_server/__init__.py
tw5_server/__main__.py
tw5_server/app.py
tw5_server/config.ini
tw5_server/errors.py
tw5_server/settings.py
tw5_server/templates/401.html
tw5_server/templates/403.html
tw5_server/templates/404.html
tw5_server/wiki/__init__.py
tw5_server/wiki/auth.py
tw5_server/wiki/storage.py
tw5_server/wiki/utils.py
tw5_server/wiki/views.py
tw5_server-1.2.0.dist-info/LICENSE
tw5_server-1.2.0.dist-info/METADATA
tw5_server-1.2.0.dist-info/WHEEL
tw5_server-1.2.0.dist-info/entry_points.txt
tw5_server-1.2.0.dist-info/top_level.txt
tw5_server-1.2.0.dist-info/RECORD
