Metadata-Version: 2.1
Name: tw5-server
Version: 1.2.0
Summary: Tiddlyspot-like server in Python
Home-page: UNKNOWN
Author: Abraham
Author-email: abraham.liu@hotmail.com
License: BSD
Project-URL: Source Code, https://github.com/zlqm/tw5_server
Project-URL: Issue Tracker, https://github.com/zlqm/tw5_server/issues/
Platform: UNKNOWN
Classifier: Development Status :: 5 - Production/Stable
Classifier: Intended Audience :: Developers
Classifier: Intended Audience :: System Administrators
Classifier: Operating System :: OS Independent
Classifier: Programming Language :: Python
Classifier: Topic :: Utilities
Requires-Python: >=3.6
Requires-Dist: Flask
